Workbook

Sheet 00 Index
A1: Excel: Basic to Advanced – practice workbook
A2: Companion to the Data Science & AI Handbook (Advanced Excel session and Building Blocks · Class 1). Black bold cells are live formulas; blue cells are inputs you can change. Brown text shows the formula used.
A4: # | B4: Sheet | C4: Topic | D4: Level
A5: 1 | B5: 01 Environment | C5: Workbook terms and 24 essential shortcuts | D5: Basic
A6: 2 | B6: 02 References | C6: Relative, absolute, mixed references; GST example; multiplication grid | D6: Basic
A7: 3 | B7: 03 Custom Formats | C7: 12 custom number formats incl. Indian lakh, ▲▼, k/M | D7: Basic
A8: 4 | B8: 04 Number | C8: ROUND, ROUNDUP, INT, MOD, ABS, CEILING, SUMPRODUCT… | D8: Basic
A9: 5 | B9: 05 Text | C9: TRIM, PROPER, LEFT/RIGHT/MID, FIND, SUBSTITUTE, TEXTJOIN, masking | D9: Basic
A10: 6 | B10: 06 Date & Time | C10: EOMONTH, EDATE, NETWORKDAYS, WORKDAY, DATEDIF, FY & quarter | D10: Basic
A11: 7 | B11: 07 Aggregate | C11: SUM…STDEV, SUMIFS/COUNTIFS/AVERAGEIFS/MAXIFS, SUBTOTAL, conditional probability | D11: Intermediate
A12: 8 | B12: 08 Logical | C12: IF, nested IF, IFS, SWITCH, AND/OR/NOT, IFERROR, IFNA | D12: Intermediate
A13: 9 | B13: 09 Lookup | C13: VLOOKUP, INDEX/MATCH, CHOOSE, HLOOKUP, slabs, XLOOKUP | D13: Intermediate
A14: 10 | B14: 10 Conditional Formatting | C14: Overdue rows, duplicates, data bars, colour scales, icons; freeze panes | D14: Intermediate
A15: 11 | B15: 11 Validation | C15: Drop-down lists, number/date/length rules, input messages | D15: Intermediate
A16: 12 | B16: 12 Sort & Filter | C16: AutoFilter, multi-level sort, SUBTOTAL, advanced filter | D16: Intermediate
... A25: 21 | B25: Lookups | C25: Products, stores, commission slabs, holidays | D25: Data
A28: Sources for 2025–26 features: Microsoft Excel blog; Excel Campus '17 New Excel Updates from 2025'. Sample data is fictional.

Sheet 01 Environment
A1: 01 · Excel environment, terminology & shortcuts
A2: Building Blocks · Class 1. Learn the vocabulary and the 30 shortcuts that save the most time.
A3: ← Index
A5: Term | B5: Meaning | C5: Example | D5: Tip
A6: Workbook | B6: The .xlsx file containing sheets | C6: Excel_Basic_to_Advanced.xlsx | D6: .xlsm if it contains macros
A7: Worksheet | B7: One grid of rows and columns | C7: Data, Lookups | D7: Double-click a tab to rename
A8: Cell / address | B8: Intersection of a column and row | C8: B7 | D8: Name Box shows the active cell
A9: Range | B9: Block of cells | C9: A1:D20 | D9: Ctrl+Shift+Arrow selects a range
A10: Formula | B10: Starts with = and calculates | C10: =G2*H2 | D10: Ctrl+` shows all formulas
A11: Function | B11: Built-in named formula | C11: =SUM(L2:L401) | D11: Shift+F3 opens Insert Function
A12: Argument | B12: Input to a function | C12: SUM(number1, number2...) | D12: Separated by commas
A13: Table | B13: Formatted, auto-expanding range | C13: Ctrl+T | D13: Use names like Sales[Amount]
A14: Named range | B14: A friendly name for cells | C14: GST_Rate | D14: Formulas → Name Manager
A15: Ribbon / QAT | B15: Command tabs / quick-access toolbar | C15: Home, Insert, Data… | D15: Right-click a command → Add to QAT
A17: Shortcuts
A18: Shortcut | B18: Action | C18: Shortcut | D18: Action
A19: Ctrl+Arrow | B19: Jump to edge of data | C19: Ctrl+1 | D19: Format Cells
A20: Ctrl+Shift+Arrow | B20: Select to edge of data | C20: Ctrl+T | D20: Create Table
A21: Ctrl+Space / Shift+Space | B21: Select column / row | C21: Ctrl+Shift+L | D21: Toggle filter
A22: Ctrl+Home / Ctrl+End | B22: First / last used cell | C22: Alt+= | D22: AutoSum
A23: Ctrl+PgUp / PgDn | B23: Previous / next sheet | C23: F4 | D23: Toggle $ references; repeat action
A24: F2 | B24: Edit cell | C24: Ctrl+; | D24: Insert today's date
A25: Ctrl+D / Ctrl+R | B25: Fill down / right | C25: Ctrl+Shift+; | D25: Insert current time
A26: Ctrl+E | B26: Flash Fill | C26: Alt+Enter | D26: New line inside a cell
A27: Ctrl+Alt+V | B27: Paste Special | C27: Ctrl+` | D27: Show formulas
A28: Alt+F1 / F11 | B28: Quick chart / chart sheet | C28: Alt+F5 / Ctrl+Alt+F5 | D28: Refresh pivot / Refresh All
A29: Ctrl+Z / Ctrl+Y | B29: Undo / Redo | C29: Alt+F11 | D29: VBA editor
A30: Ctrl+F / Ctrl+H | B30: Find / Replace | C30: Ctrl+G or F5 | D30: Go To (Special)

Sheet 02 References
A1: 02 · Cell references: relative, absolute, mixed
A2: Change the blue GST rate in C4 and watch every row update. The $ in $C$4 keeps the reference fixed when the formula is copied down.
A3: ← Index
B4: GST rate | C4: 0.18
A6: Product | B6: Price (₹) | C6: GST (₹) | D6: Price incl. GST | E6: Formula in C (copied down) | F6: Reference type
A7: Earbuds | B7: 2999 | C7: =B7*$C$4 | D7: =B7+C7 | E7: =B7*$C$4 | F7: B relative, $C$4 absolute
A8: Power Bank | B8: 1799 | C8: =B8*$C$4 | D8: =B8+C8 | E8: =B8*$C$4 | F8: B relative, $C$4 absolute
A9: Speaker | B9: 4499 | C9: =B9*$C$4 | D9: =B9+C9 | E9: =B9*$C$4 | F9: B relative, $C$4 absolute
A10: Charger | B10: 1499 | C10: =B10*$C$4 | D10: =B10+C10 | E10: =B10*$C$4 | F10: B relative, $C$4 absolute
A13: Mixed references: multiplication grid
A14: × | B14: 1 | C14: 2 | D14: 3 | E14: 4 | F14: 5
A15: 1 | B15: =$A15*B$14 | C15: =$A15*C$14 | D15: =$A15*D$14 | E15: =$A15*E$14 | F15: =$A15*F$14
A16: 2 | B16: =$A16*B$14 | C16: =$A16*C$14 | D16: =$A16*D$14 | E16: =$A16*E$14 | F16: =$A16*F$14
A17: 3 | B17: =$A17*B$14 | C17: =$A17*C$14 | D17: =$A17*D$14 | E17: =$A17*E$14 | F17: =$A17*F$14
A18: 4 | B18: =$A18*B$14 | C18: =$A18*C$14 | D18: =$A18*D$14 | E18: =$A18*E$14 | F18: =$A18*F$14
A19: 5 | B19: =$A19*B$14 | C19: =$A19*C$14 | D19: =$A19*D$14 | E19: =$A19*E$14 | F19: =$A19*F$14
A21: Formula in B15, copied to the whole grid: =$A15*B$14 ($A locks the column, $14 locks the row)

Sheet 03 Custom Formats
A1: 03 · Formatting & custom number formats
A2: The value in column B is the same in every row; only the number format in column C changes how it looks (Ctrl+1 → Custom).
A3: ← Index
A5: Purpose | B5: Value | C5: Displayed as | D5: Custom format code | E5: Note
A6: Thousands separator | B6: 1250000 | C6: =B6 | D6: #,##0 | E6: Standard grouping
A7: Indian lakh/crore grouping | B7: 1250000 | C7: =B7 | D7: [>=10000000]##\,##\,##\,##0;[>=100000]##\,##\,##0;##,##0 | E7: 12,50,000
A8: Millions | B8: 1250000 | C8: =B8 | D8: 0.0,,"M" | E8: Each comma divides by 1,000
A9: Rupee currency | B9: 99.5 | C9: =B9 | D9: "₹"#,##0.00 | E9: Currency with symbol
A10: Fixed-length ID | B10: 7 | C10: =B10 | D10: 000 | E10: Shows 007
A11: Readable date | B11: 31541 | C11: =B11 | D11: dd mmm' yyyy | E11: 09 May' 1986
A12: Units while numeric | B12: 80 | C12: =B12 | D12: 0 "kg" | E12: Still a number for maths
A13: Up/down arrows | B13: 0.12 | C13: =B13 | D13: [Color10]▲0%;[Red]▼0%;0% | E13: positive;negative;zero
A14: Negative in brackets | B14: -45200 | C14: =B14 | D14: #,##0;(#,##0);- | E14: Finance style; zero shows -
A15: Thousands with k | B15: 87670 | C15: =B15 | D15: [<100000]0.00,"k";0.0,"k" | E15: 87.67k; ≥100000 one decimal
A16: Percentage | B16: 0.0765 | C16: =B16 | D16: 0.0% | E16: Stored as a fraction
A17: Hide value | B17: 12345 | C17: =B17 | D17: ;;; | E17: Value kept but invisible
A20: Format has up to 4 sections: positive ; negative ; zero ; text. Conditions like [<100000] can replace them.

Sheet 04 Number
A1: 04 · Number functions
A2: Real-world examples on a single order: change the blue inputs.
A3: ← Index
A5: Order amount (₹) | B5: 12345.678
A6: Quantity | B6: 37
A7: Carton size | B7: 12
A9: Function | B9: Formula | C9: Result | D9: Business use
A10: ROUND | B10: =ROUND(B5*18%,2) | C10: =ROUND(B5*18%,2) | D10: GST at 18% to paise
A11: ROUNDUP | B11: =ROUNDUP(B6/B7,0) | C11: =ROUNDUP(B6/B7,0) | D11: Cartons needed (12 per carton)
A12: ROUNDDOWN | B12: =ROUNDDOWN(B5,-2) | C12: =ROUNDDOWN(B5,-2) | D12: Round down to hundreds
A13: INT | B13: =INT(B5/1000) | C13: =INT(B5/1000) | D13: Whole thousands
A14: MOD | B14: =MOD(B6,B7) | C14: =MOD(B6,B7) | D14: Loose units left over
A15: ABS | B15: =ABS(9500-B5) | C15: =ABS(9500-B5) | D15: Size of miss vs target 9,500
A16: CEILING.MATH | B16: =CEILING.MATH(B5,10) | C16: =_xlfn.CEILING.MATH(B5,10) | D16: Price rounded up to next ₹10
A17: POWER | B17: =POWER(1.12,5) | C17: =POWER(1.12,5) | D17: Growth factor at 12% for 5 years
A18: SQRT | B18: =SQRT(144) | C18: =SQRT(144) | D18: Square root
A19: SUMPRODUCT | B19: =SUMPRODUCT(Data!G2:G401,Data!H2:H401) | C19: =SUMPRODUCT(Data!G2:G401,Data!H2:H401) | D19: Gross sales without a helper column
A20: RANDBETWEEN | B20: =RANDBETWEEN(1,100) | D20: Random sample IDs (recalculates every change, so no live value here)

Sheet 05 Text
A1: 05 · Text functions
A2: Cleaning messy imported text. Inputs in blue.
A3: ← Index
A5: Full name | B5: ravi kumar
A6: Email | B6: Asha.Verma@Example.com
A7: Order code | B7: NOR-1042-MUM
A8: Phone | B8: 9876543210
A9: Price text | B9: ₹1,250
A11: Function | B11: Formula | C11: Result | D11: Use
A12: TRIM + PROPER | B12: =PROPER(TRIM(B5)) | C12: =PROPER(TRIM(B5)) | D12: Tidy names
A13: LEFT | B13: =LEFT(B7,3) | C13: =LEFT(B7,3) | D13: Region prefix
A14: RIGHT | B14: =RIGHT(B7,3) | C14: =RIGHT(B7,3) | D14: City suffix
A15: MID + FIND | B15: =MID(B7,FIND("-",B7)+1,4) | C15: =MID(B7,FIND("-",B7)+1,4) | D15: Middle part
A16: LEN | B16: =LEN(B8)=10 | C16: =LEN(B8)=10 | D16: Valid 10-digit mobile?
A17: Domain | B17: =MID(B6,FIND("@",B6)+1,50) | C17: =MID(B6,FIND("@",B6)+1,50) | D17: Email domain
A18: LOWER | B18: =LOWER(B6) | C18: =LOWER(B6) | D18: Standardise emails
A19: UPPER | B19: =UPPER(B7) | C19: =UPPER(B7) | D19: Codes in capitals
A20: SUBSTITUTE + VALUE | B20: =VALUE(SUBSTITUTE(SUBSTITUTE(B9,"₹",""),",","")) | C20: =VALUE(SUBSTITUTE(SUBSTITUTE(B9,"₹",""),",","")) | D20: Text price → number
A21: Mask | B21: ="XXXXXX"&RIGHT(B8,4) | C21: ="XXXXXX"&RIGHT(B8,4) | D21: Hide phone digits
A22: CONCAT / & | B22: =PROPER(TRIM(B5))&" ("&RIGHT(B7,3)&")" | C22: =PROPER(TRIM(B5))&" ("&RIGHT(B7,3)&")" | D22: Build labels
A23: TEXTJOIN | B23: =TEXTJOIN(", ",TRUE,Lookups!I3:I8) | C23: =_xlfn.TEXTJOIN(", ",TRUE,Lookups!I3:I8) | D23: List of cities in one cell
A24: Word count | B24: =LEN(TRIM(B5))-LEN(SUBSTITUTE(TRIM(B5)," ",""))+1 | C24: =LEN(TRIM(B5))-LEN(SUBSTITUTE(TRIM(B5)," ",""))+1 | D24: Words in a cell
A25: TEXT | B25: =TEXT(1234.5,"₹#,##0.00") | C25: =TEXT(1234.5,"₹#,##0.00") | D25: Number as formatted text

Sheet 06 Date & Time
A1: 06 · Date & time functions
A2: Dates are serial numbers. Inputs in blue; Holidays list on the Lookups sheet.
A3: ← Index
A5: Order date | B5: 46304
A6: Delivered | B6: 46316
A7: Date of birth | B7: 33039
A8: Login | B8: 46304.385
A9: Logout | B9: 46304.778
A11: Function | B11: Formula | C11: Result | D11: Use
A12: YEAR / MONTH / DAY | B12: =YEAR(B5) | C12: =YEAR(B5) | D12: Group by year
A13: TEXT month | B13: =TEXT(B5,"mmm-yy") | C13: =TEXT(B5,"mmm-yy") | D13: Month label
A14: Weekday name | B14: =TEXT(B5,"dddd") | C14: =TEXT(B5,"dddd") | D14: Day of week
A15: DATE | B15: =DATE(2026,4,1) | C15: =DATE(2026,4,1) | D15: Start of FY 2026-27
A16: EOMONTH | B16: =EOMONTH(B5,0) | C16: =EOMONTH(B5,0) | D16: Month-end (billing cut-off)
A17: First of month | B17: =EOMONTH(B5,-1)+1 | C17: =EOMONTH(B5,-1)+1 | D17: Month start
A18: EDATE | B18: =EDATE(B5,3) | C18: =EDATE(B5,3) | D18: Warranty check after 3 months
A19: Days between | B19: =B6-B5 | C19: =B6-B5 | D19: Delivery days (calendar)
A20: NETWORKDAYS | B20: =NETWORKDAYS(B5,B6,Lookups!O3:O6) | C20: =NETWORKDAYS(B5,B6,Lookups!O3:O6) | D20: Working days excl. weekends & holidays
A21: WORKDAY | B21: =WORKDAY(B5,10,Lookups!O3:O6) | C21: =WORKDAY(B5,10,Lookups!O3:O6) | D21: SLA due date: 10 working days
A22: DATEDIF | B22: =DATEDIF(B7,B5,"Y") | C22: =DATEDIF(B7,B5,"Y") | D22: Age in completed years on order date
A23: WEEKNUM | B23: =WEEKNUM(B5,2) | C23: =WEEKNUM(B5,2) | D23: Week number (Mon start)
A24: Financial year | B24: ="FY"&IF(MONTH(B5)>=4,YEAR(B5)+1,YEAR(B5)) | C24: ="FY"&IF(MONTH(B5)>=4,YEAR(B5)+1,YEAR(B5)) | D24: Indian FY label
A25: FY quarter | B25: ="Q"&ROUNDUP((MOD(MONTH(B5)-4,12)+1)/3,0) | C25: ="Q"&ROUNDUP((MOD(MONTH(B5)-4,12)+1)/3,0) | D25: Apr–Jun = Q1
A26: Hours worked | B26: =(B9-B8)*24 | C26: =(B9-B8)*24 | D26: Shift length in hours

Sheet 07 Aggregate
A1: 07 · Aggregate & conditional aggregate functions
A2: All formulas read the 400-order Data sheet. Change the blue city / dates to re-run.
A3: ← Index
A5: City | B5: Pune
A6: From | B6: 46204
A7: To | B7: 46295
A9: Function | B9: Formula | C9: Result | D9: Answer to
A10: SUM | B10: =SUM(Data!$L$2:$L$401) | C10: =SUM(Data!$L$2:$L$401) | D10: Total revenue
A11: COUNT / COUNTA | B11: =COUNTA(Data!$A$2:$A$401) | C11: =COUNTA(Data!$A$2:$A$401) | D11: Number of orders
A12: AVERAGE | B12: =AVERAGE(Data!$L$2:$L$401) | C12: =AVERAGE(Data!$L$2:$L$401) | D12: Average order value
A13: MEDIAN | B13: =MEDIAN(Data!$L$2:$L$401) | C13: =MEDIAN(Data!$L$2:$L$401) | D13: Typical order (skew-proof)
A14: MAX / LARGE | B14: =LARGE(Data!$L$2:$L$401,3) | C14: =LARGE(Data!$L$2:$L$401,3) | D14: 3rd largest order
A15: MIN / SMALL | B15: =SMALL(Data!$L$2:$L$401,1) | C15: =SMALL(Data!$L$2:$L$401,1) | D15: Smallest order
A16: COUNTBLANK | B16: =COUNTBLANK(Data!$D$2:$D$401) | C16: =COUNTBLANK(Data!$D$2:$D$401) | D16: Orders missing a city
A17: SUMIF | B17: =SUMIF(Data!$D$2:$D$401,B5,Data!$L$2:$L$401) | C17: =SUMIF(Data!$D$2:$D$401,B5,Data!$L$2:$L$401) | D17: Revenue for the chosen city
A18: SUMIFS (city + dates) | B18: =SUMIFS(Data!$L$2:$L$401,Data!$D$2:$D$401,B5,Data!$B$2:$B$401,">="&B6,Data!$B$2:$B$401,"<="&B7) | C18: =SUMIFS(Data!$L$2:$L$401,Data!$D$2:$D$401,B5,Data!$B$2:$B$401,">="&B6,Data!$B$2:$B$401,"<="&B7) | D18: City revenue between two dates
A19: COUNTIFS | B19: =COUNTIFS(Data!$D$2:$D$401,B5,Data!$L$2:$L$401,">20000") | C19: =COUNTIFS(Data!$D$2:$D$401,B5,Data!$L$2:$L$401,">20000") | D19: Big orders in the city
A20: AVERAGEIFS | B20: =AVERAGEIFS(Data!$L$2:$L$401,Data!$F$2:$F$401,"Laptops") | C20: =AVERAGEIFS(Data!$L$2:$L$401,Data!$F$2:$F$401,"Laptops") | D20: Average laptop order
A21: MAXIFS | B21: =MAXIFS(Data!$L$2:$L$401,Data!$D$2:$D$401,B5) | C21: =_xlfn.MAXIFS(Data!$L$2:$L$401,Data!$D$2:$D$401,B5) | D21: Biggest order in the city
A22: OR across cities | B22: =SUM(SUMIFS(Data!$L$2:$L$401,Data!$D$2:$D$401,{"Pune","Mumbai"})) | C22: =SUMPRODUCT(SUMIFS(Data!$L$2:$L$401,Data!$D$2:$D$401,{"Pune","Mumbai"})) | D22: Maharashtra revenue
A23: Conditional probability | B23: =COUNTIFS(Data!$J$2:$J$401,"Walk-in",Data!$K$2:$K$401,"Yes")/COUNTIF(Data!$J$2:$J$401,"Walk-in") | C23: =COUNTIFS(Data!$J$2:$J$401,"Walk-in",Data!$K$2:$K$401,"Yes")/COUNTIF(Data!$J$2:$J$401,"Walk-in") | D23: P(warranty | walk-in)
A24: RANK.EQ | B24: =RANK.EQ(C10,C10:C12) | D24: Rank a value in a list (see Dashboard sheet)
A25: STDEV.S | B25: =STDEV.S(Data!$L$2:$L$401) | C25: =_xlfn.STDEV.S(Data!$L$2:$L$401) | D25: Spread of order values
A26: SUBTOTAL (visible) | B26: =SUBTOTAL(109,Data!$L$2:$L$401) | C26: =SUBTOTAL(109,Data!$L$2:$L$401) | D26: Sum that ignores filtered-out rows

Sheet 08 Logical
A1: 08 · Logical functions & error handling
A2: Customer tiering and data checks on sample rows (blue inputs).
A3: ← Index
A5: Customer | B5: Spend (₹) | C5: Prime? | D5: City | E5: Tier (nested IF) | F5: Tier (IFS) | G5: Zone (SWITCH)
A6: C01 | B6: 72000 | C6: Yes | D6: Pune | E6: =IF(B6>=50000,"Gold",IF(B6>=20000,"Silver","Bronze")) | F6: =_xlfn.IFS(B6>=50000,"Gold",B6>=20000,"Silver",TRUE,"Bronze") | G6: =_xlfn.SWITCH(D6,"Pune","West","Mumbai","West","Delhi","North","South")
A7: C02 | B7: 31000 | C7: No | D7: Delhi | E7: =IF(B7>=50000,"Gold",IF(B7>=20000,"Silver","Bronze")) | F7: =_xlfn.IFS(B7>=50000,"Gold",B7>=20000,"Silver",TRUE,"Bronze") | G7: =_xlfn.SWITCH(D7,"Pune","West","Mumbai","West","Delhi","North","South")
A8: C03 | B8: 8000 | C8: Yes | D8: Mumbai | E8: =IF(B8>=50000,"Gold",IF(B8>=20000,"Silver","Bronze")) | F8: =_xlfn.IFS(B8>=50000,"Gold",B8>=20000,"Silver",TRUE,"Bronze") | G8: =_xlfn.SWITCH(D8,"Pune","West","Mumbai","West","Delhi","North","South")
A9: C04 | B9: 0 | C9: No | D9: Chennai | E9: =IF(B9>=50000,"Gold",IF(B9>=20000,"Silver","Bronze")) | F9: =_xlfn.IFS(B9>=50000,"Gold",B9>=20000,"Silver",TRUE,"Bronze") | G9: =_xlfn.SWITCH(D9,"Pune","West","Mumbai","West","Delhi","North","South")
A11: Function | B11: Formula (row 6) | E11: Result | F11: Use
A12: AND | B12: =IF(AND(B6>50000,C6="Yes"),"VIP","-") | E12: =IF(AND(B6>50000,C6="Yes"),"VIP","-") | F12: Both conditions
A13: OR | B13: =IF(OR(D7="Pune",D7="Mumbai"),"MH","Other") | E13: =IF(OR(D7="Pune",D7="Mumbai"),"MH","Other") | F13: Either condition
A14: NOT | B14: =NOT(C8="Yes") | E14: =NOT(C8="Yes") | F14: Reverse a test
A15: IFERROR | B15: =IFERROR(100000/B9,0) | E15: =IFERROR(100000/B9,0) | F15: Avoid divide-by-zero errors
A16: IFNA | B16: =IFNA(MATCH("C09",A6:A9,0),"Not found") | E16: =_xlfn.IFNA(MATCH("C09",A6:A9,0),"Not found") | F16: Friendly lookup miss
A17: ISNUMBER+SEARCH | B17: =ISNUMBER(SEARCH("pun",D6)) | E17: =ISNUMBER(SEARCH("pun",D6)) | F17: Text contains

Sheet 09 Lookup
A1: 09 · Lookup functions: VLOOKUP → INDEX/MATCH → XLOOKUP
A2: Find details for the product ID in B5. Lookup tables are on the Lookups sheet.
A3: ← Index
A5: Product ID | B5: P302
A6: Rep sales (₹) | B6: 340000
A8: Method | B8: Formula | C8: Result | D8: Note
A9: VLOOKUP exact | B9: =VLOOKUP(B5,Lookups!$A$3:$E$12,2,FALSE) | C9: =VLOOKUP(B5,Lookups!$A$3:$E$12,2,FALSE) | D9: Name: column 2 of the table
A10: VLOOKUP price | B10: =VLOOKUP(B5,Lookups!$A$3:$E$12,4,FALSE) | C10: =VLOOKUP(B5,Lookups!$A$3:$E$12,4,FALSE) | D10: List price
A11: INDEX + MATCH | B11: =INDEX(Lookups!$C$3:$C$12,MATCH(B5,Lookups!$A$3:$A$12,0)) | C11: =INDEX(Lookups!$C$3:$C$12,MATCH(B5,Lookups!$A$3:$A$12,0)) | D11: Category; works in any direction
A12: Reverse lookup | B12: =INDEX(Lookups!$A$3:$A$12,MATCH("Charger 65W",Lookups!$B$3:$B$12,0)) | C12: =INDEX(Lookups!$A$3:$A$12,MATCH("Charger 65W",Lookups!$B$3:$B$12,0)) | D12: ID from name (left of the key)
A13: VLOOKUP + CHOOSE | B13: =VLOOKUP("Charger 65W",CHOOSE({1,2},Lookups!$B$3:$B$12,Lookups!$A$3:$A$12),2,FALSE) | C13: =VLOOKUP("Charger 65W",CHOOSE({1,2},Lookups!$B$3:$B$12,Lookups!$A$3:$A$12),2,FALSE) | D13: Classic left-lookup trick
A14: HLOOKUP | B14: =HLOOKUP("City",Lookups!$G$2:$J$8,3,FALSE) | C14: =HLOOKUP("City",Lookups!$G$2:$J$8,3,FALSE) | D14: Look across a header row
A15: Two-way INDEX/MATCH | B15: =INDEX(Lookups!$A$3:$E$12,MATCH(B5,Lookups!$A$3:$A$12,0),MATCH("UnitCost",Lookups!$A$2:$E$2,0)) | C15: =INDEX(Lookups!$A$3:$E$12,MATCH(B5,Lookups!$A$3:$A$12,0),MATCH("UnitCost",Lookups!$A$2:$E$2,0)) | D15: Row by ID, column by header
A16: Approximate (slabs) | B16: =VLOOKUP(B6,Lookups!$L$3:$M$6,2,TRUE) | C16: =VLOOKUP(B6,Lookups!$L$3:$M$6,2,TRUE) | D16: Commission rate for sales in B6
A17: Commission | B17: =B6*VLOOKUP(B6,Lookups!$L$3:$M$6,2,TRUE) | C17: =B6*VLOOKUP(B6,Lookups!$L$3:$M$6,2,TRUE) | D17: ₹ commission
A18: Not-found handling | B18: =IFERROR(VLOOKUP("P999",Lookups!$A$3:$E$12,2,FALSE),"Missing") | C18: =IFERROR(VLOOKUP("P999",Lookups!$A$3:$E$12,2,FALSE),"Missing") | D18: Friendly message
A20: Excel 365 / 2021 only (type these in Excel 365; expected result shown)
A21: Function | B21: Formula | C21: Expected result | D21: Why it's better
A22: XLOOKUP | B22: =XLOOKUP(B5,Lookups!A3:A12,Lookups!B3:B12,"Missing") | C22: Bluetooth Speaker | D22: Any direction + built-in not-found
A23: XLOOKUP whole row | B23: =XLOOKUP(B5,Lookups!A3:A12,Lookups!B3:E12) | C23: Bluetooth Speaker | Audio | 4499 | 2900 | D23: Returns several columns at once
A24: XLOOKUP slab | B24: =XLOOKUP(B6,Lookups!L3:L6,Lookups!M3:M6,,-1) | C24: 3% | D24: -1 = exact or next smaller
A25: XMATCH | B25: =XMATCH("Laptop 14in",Lookups!B3:B12) | C25: 3 | D25: Position, with search modes

Sheet 10 Conditional Formatting
A1: 10 · Conditional formatting (rules already applied)
A2: Home → Conditional Formatting → Manage Rules to see each rule. Change the blue numbers to see formats move.
A3: ← Index
A5: Invoice | B5: Due date | C5: Status | D5: Amount (₹) | E5: Margin % | F5: Score | G5: Rules applied
A6: INV-01 | B6: 46295 | C6: Unpaid | D6: 52000 | E6: 0.22 | F6: 88 | G6: Whole row red: =AND($B6<DATE(2026,10,27),$C6="Unpaid") (overdue as of 27-Oct-2026)
A7: INV-02 | B7: 46341 | C7: Unpaid | D7: 18000 | E7: -0.05 | F7: 45 | G7: Duplicate invoice IDs amber: =COUNTIF($A$6:$A$11,$A6)>1
A8: INV-03 | B8: 46300 | C8: Paid | D8: 74000 | E8: 0.31 | F8: 92 | G8: Data bars on Amount
A9: INV-04 | B9: 46254 | C9: Unpaid | D9: 9000 | E9: 0.08 | F9: 61 | G9: Negative margin red text: Cell Value < 0
A10: INV-05 | B10: 46357 | C10: Paid | D10: 33000 | E10: 0.15 | F10: 73 | G10: 3-colour scale on Score
A11: INV-01 | B11: 46320 | C11: Unpaid | D11: 61000 | E11: 0.19 | F11: 80
A14: More custom rules to try: zebra rows =MOD(ROW(),2)=0 · weekends =WEEKDAY($B6,2)>5 · top 10% → Top/Bottom rules
A16: Freeze panes is set on this sheet (View → Freeze Panes): rows above row 6 stay visible while scrolling.

Sheet 11 Validation
A1: 11 · Data validation (drop-downs and input rules)
A2: Click the yellow cells: each has a rule (Data → Data Validation).
A3: ← Index
A5: City (drop-down list) | B5: Pune | C5: List source: "Mumbai,Pune,Delhi,Bengaluru,Chennai,Gurugram"
A6: Product ID (list from a range) | B6: P101 | C6: List source: =Lookups!$A$3:$A$12
A7: Quantity (whole number 1–50) | B7: 2 | C7: Whole number between 1 and 50
A8: Order date (FY 2026-27 only) | B8: 46174 | C8: Date between 01-Apr-2026 and 31-Mar-2027
A9: Mobile (exactly 10 characters) | B9: 9876543210 | C9: Text length = 10
A11: Dependent drop-down idea: name each category's product list, then use =INDIRECT(B5) as the list source of the next cell.

Sheet 12 Sort & Filter
A1: 12 · Sorting, filters & freeze panes
A2: This copy of 40 orders has AutoFilter on (row 5) and frozen headers. Try: Data → Sort (City A–Z then Amount largest), filter Category = Laptops, then watch SUBTOTAL change.
A3: ← Index
A5: OrderID | B5: OrderDate | C5: City | D5: Category | E5: Amount | G5: SUM (all rows) | H5: =SUM(E6:E45)
A6: ORD-0165 | B6: 46113 | C6: Mumbai | D6: Laptops | E6: 54999 | G6: SUBTOTAL(109) (visible only) | H6: =SUBTOTAL(109,E6:E45)
A7: ORD-0174 | B7: 46113 | C7: Bengaluru | D7: Accessories | E7: 1619
A8: ORD-0334 | B8: 46113 | C8: Delhi | D8: Accessories | E8: 1499 | G8: Advanced Filter: Data → Advanced, criteria range G10:H11 (same row = AND).
A9: ORD-0118 | B9: 46114 | C9: Bengaluru | D9: Audio | E9: 2849
A10: ORD-0130 | B10: 46114 | C10: Mumbai | D10: Accessories | E10: 4497 | G10: City | H10: Amount
A11: ORD-0200 | B11: 46115 | C11: Pune | D11: Audio | E11: 4274 | G11: Pune | H11: >20000
A12: ORD-0266 | B12: 46115 | C12: Delhi | D12: Mobiles | E12: 62698
A13: ORD-0327 | B13: 46115 | C13: Mumbai | D13: Mobiles | E13: 18999
A14: ORD-0017 | B14: 46118 | C14: Chennai | D14: TV | E14: 32999
A15: ORD-0277 | B15: 46118 | C15: Mumbai | D15: Accessories | E15: 1619
A16: ORD-0302 | B16: 46118 | C16: Pune | D16: Laptops | E16: 284997
A17: ORD-0397 | B17: 46118 | C17: Gurugram | D17: Mobiles | E17: 29699
A18: ORD-0021 | B18: 46119 | C18: Mumbai | D18: Mobiles | E18: 32999
A19: ORD-0381 | B19: 46119 | C19: Pune | D19: TV | E19: 100698
A20: ORD-0005 | B20: 46120 | C20: Mumbai | D20: Accessories | E20: 3238
A21: ORD-0031 | B21: 46120 | C21: Bengaluru | D21: Laptops | E21: 94999
A22: ORD-0138 | B22: 46120 | C22: Bengaluru | D22: Audio | E22: 5698
A23: ORD-0125 | B23: 46121 | C23: Bengaluru | D23: Accessories | E23: 2998
... A45: ORD-0127 | B45: 46133 | C45: Mumbai | D45: Audio | E45: 5398

Sheet 13 Pivot
A1: 13 · Pivot tables (steps) + the same summary with formulas
A2: Build a real pivot from the Data sheet with the steps below. The grid on the right is a SUMIFS 'formula pivot' so you can check your numbers.
A3: ← Index
A5: 1. Click any cell in Data → Insert → PivotTable → New Worksheet.
A6: 2. Rows: City. Columns: Category. Values: Sum of Amount.
A7: 3. Value Field Settings → Number Format #,##0.
A8: 4. Right-click OrderDate in Rows → Group → Months (and Years).
A9: 5. Show Values As → % of Grand Total (or % of Row).
A10: 6. Insert → Slicer: CustomerType; Insert → Timeline: OrderDate.
A11: 7. Design → Report Layout → Tabular; Grand Totals on/off.
A12: 8. Refresh after data changes: Alt+F5; Refresh All: Ctrl+Alt+F5.
A13: 9. Calculated Field: Margin = Profit / Amount (PivotTable Analyze → Fields, Items & Sets).
A16: Sum of Amount (₹) | B16: Mobiles | C16: Laptops | D16: Audio | E16: Accessories | F16: TV | G16: Total
A17: Mumbai | B17: =SUMIFS(Data!$L$2:$L$401,Data!$D$2:$D$401,$A17,Data!$F$2:$F$401,B$16) | C17: =SUMIFS(Data!$L$2:$L$401,Data!$D$2:$D$401,$A17,Data!$F$2:$F$401,C$16) | D17: =SUMIFS(Data!$L$2:$L$401,Data!$D$2:$D$401,$A17,Data!$F$2:$F$401,D$16) | E17: =SUMIFS(Data!$L$2:$L$401,Data!$D$2:$D$401,$A17,Data!$F$2:$F$401,E$16) | F17: =SUMIFS(Data!$L$2:$L$401,Data!$D$2:$D$401,$A17,Data!$F$2:$F$401,F$16) | G17: =SUM(B17:F17)
A18: Pune | B18: =SUMIFS(Data!$L$2:$L$401,Data!$D$2:$D$401,$A18,Data!$F$2:$F$401,B$16) | C18: =SUMIFS(Data!$L$2:$L$401,Data!$D$2:$D$401,$A18,Data!$F$2:$F$401,C$16) | D18: =SUMIFS(Data!$L$2:$L$401,Data!$D$2:$D$401,$A18,Data!$F$2:$F$401,D$16) | E18: =SUMIFS(Data!$L$2:$L$401,Data!$D$2:$D$401,$A18,Data!$F$2:$F$401,E$16) | F18: =SUMIFS(Data!$L$2:$L$401,Data!$D$2:$D$401,$A18,Data!$F$2:$F$401,F$16) | G18: =SUM(B18:F18)
A19: Delhi | B19: =SUMIFS(Data!$L$2:$L$401,Data!$D$2:$D$401,$A19,Data!$F$2:$F$401,B$16) | C19: =SUMIFS(Data!$L$2:$L$401,Data!$D$2:$D$401,$A19,Data!$F$2:$F$401,C$16) | D19: =SUMIFS(Data!$L$2:$L$401,Data!$D$2:$D$401,$A19,Data!$F$2:$F$401,D$16) | E19: =SUMIFS(Data!$L$2:$L$401,Data!$D$2:$D$401,$A19,Data!$F$2:$F$401,E$16) | F19: =SUMIFS(Data!$L$2:$L$401,Data!$D$2:$D$401,$A19,Data!$F$2:$F$401,F$16) | G19: =SUM(B19:F19)
A20: Bengaluru | B20: =SUMIFS(Data!$L$2:$L$401,Data!$D$2:$D$401,$A20,Data!$F$2:$F$401,B$16) | C20: =SUMIFS(Data!$L$2:$L$401,Data!$D$2:$D$401,$A20,Data!$F$2:$F$401,C$16) | D20: =SUMIFS(Data!$L$2:$L$401,Data!$D$2:$D$401,$A20,Data!$F$2:$F$401,D$16) | E20: =SUMIFS(Data!$L$2:$L$401,Data!$D$2:$D$401,$A20,Data!$F$2:$F$401,E$16) | F20: =SUMIFS(Data!$L$2:$L$401,Data!$D$2:$D$401,$A20,Data!$F$2:$F$401,F$16) | G20: =SUM(B20:F20)
A21: Chennai | B21: =SUMIFS(Data!$L$2:$L$401,Data!$D$2:$D$401,$A21,Data!$F$2:$F$401,B$16) | C21: =SUMIFS(Data!$L$2:$L$401,Data!$D$2:$D$401,$A21,Data!$F$2:$F$401,C$16) | D21: =SUMIFS(Data!$L$2:$L$401,Data!$D$2:$D$401,$A21,Data!$F$2:$F$401,D$16) | E21: =SUMIFS(Data!$L$2:$L$401,Data!$D$2:$D$401,$A21,Data!$F$2:$F$401,E$16) | F21: =SUMIFS(Data!$L$2:$L$401,Data!$D$2:$D$401,$A21,Data!$F$2:$F$401,F$16) | G21: =SUM(B21:F21)
A22: Gurugram | B22: =SUMIFS(Data!$L$2:$L$401,Data!$D$2:$D$401,$A22,Data!$F$2:$F$401,B$16) | C22: =SUMIFS(Data!$L$2:$L$401,Data!$D$2:$D$401,$A22,Data!$F$2:$F$401,C$16) | D22: =SUMIFS(Data!$L$2:$L$401,Data!$D$2:$D$401,$A22,Data!$F$2:$F$401,D$16) | E22: =SUMIFS(Data!$L$2:$L$401,Data!$D$2:$D$401,$A22,Data!$F$2:$F$401,E$16) | F22: =SUMIFS(Data!$L$2:$L$401,Data!$D$2:$D$401,$A22,Data!$F$2:$F$401,F$16) | G22: =SUM(B22:F22)
A23: Total | B23: =SUM(B17:B22) | C23: =SUM(C17:C22) | D23: =SUM(D17:D22) | E23: =SUM(E17:E22) | F23: =SUM(F17:F22) | G23: =SUM(G17:G22)
A25: Excel 365 formula pivots: =GROUPBY(Data!D2:D401, Data!L2:L401, SUM) and =PIVOTBY(Data!D2:D401, Data!F2:F401, Data!L2:L401, SUM)

Sheet 14 What-If
A1: 14 · What-if analysis: EMI, sensitivity grid, Goal Seek, break-even
A2: Change the blue inputs. The grid is built with formulas (a 2-variable Data Table gives the same result: Data → What-If → Data Table).
A3: ← Index
A5: Loan amount (₹) | B5: 1000000
A6: Annual rate | B6: 0.09
A7: Years | B7: 5
A8: Monthly EMI | B8: =PMT(B6/12,B7*12,-B5) | C8: =PMT(rate/12, months, -loan)
A9: Total interest | B9: =B8*B7*12-B5
A11: EMI sensitivity: rate × years
A12: Rate \ Years | B12: 3 | C12: 4 | D12: 5 | E12: 6 | F12: 7
A13: 0.08 | B13: =PMT($A13/12,B$12*12,-$B$5) | C13: =PMT($A13/12,C$12*12,-$B$5) | D13: =PMT($A13/12,D$12*12,-$B$5) | E13: =PMT($A13/12,E$12*12,-$B$5) | F13: =PMT($A13/12,F$12*12,-$B$5)
A14: 0.085 | B14: =PMT($A14/12,B$12*12,-$B$5) | C14: =PMT($A14/12,C$12*12,-$B$5) | D14: =PMT($A14/12,D$12*12,-$B$5) | E14: =PMT($A14/12,E$12*12,-$B$5) | F14: =PMT($A14/12,F$12*12,-$B$5)
A15: 0.09 | B15: =PMT($A15/12,B$12*12,-$B$5) | C15: =PMT($A15/12,C$12*12,-$B$5) | D15: =PMT($A15/12,D$12*12,-$B$5) | E15: =PMT($A15/12,E$12*12,-$B$5) | F15: =PMT($A15/12,F$12*12,-$B$5)
A16: 0.095 | B16: =PMT($A16/12,B$12*12,-$B$5) | C16: =PMT($A16/12,C$12*12,-$B$5) | D16: =PMT($A16/12,D$12*12,-$B$5) | E16: =PMT($A16/12,E$12*12,-$B$5) | F16: =PMT($A16/12,F$12*12,-$B$5)
A17: 0.1 | B17: =PMT($A17/12,B$12*12,-$B$5) | C17: =PMT($A17/12,C$12*12,-$B$5) | D17: =PMT($A17/12,D$12*12,-$B$5) | E17: =PMT($A17/12,E$12*12,-$B$5) | F17: =PMT($A17/12,F$12*12,-$B$5)
A18: 0.11 | B18: =PMT($A18/12,B$12*12,-$B$5) | C18: =PMT($A18/12,C$12*12,-$B$5) | D18: =PMT($A18/12,D$12*12,-$B$5) | E18: =PMT($A18/12,E$12*12,-$B$5) | F18: =PMT($A18/12,F$12*12,-$B$5)
A20: Break-even
A21: Fixed cost per month (₹) | B21: 450000
A22: Price per unit (₹) | B22: 2999
A23: Variable cost per unit (₹) | B23: 1650
A24: Break-even units | B24: =ROUNDUP(B21/(B22-B23),0)
A26: Goal Seek: Data → What-If → Goal Seek → Set cell B8, To value 18000, By changing B7 (or B5) → finds the tenure/loan that gives ₹18,000 EMI.
A27: Scenario Manager: save Best/Base/Worst sets of B21:B23 and create a summary report. Solver (add-in): optimise with constraints.

Sheet 15 Dynamic Arrays
A1: 15 · Modern Excel 365 functions (type these in Excel 365)
A2: These functions spill results into many cells. They are shown as text with the expected result computed from the Data sheet, because they need Excel 365 / 2021+.
A3: ← Index
A5: Function | B5: Formula to type in Excel 365 | C5: Expected result (from this data)
A6: UNIQUE | B6: =UNIQUE(Data!D2:D401) | C6: Bengaluru, Chennai, Delhi, Gurugram, Mumbai, Pune
A7: SORT | B7: =SORT(UNIQUE(Data!F2:F401)) | C7: Accessories, Audio, Laptops, Mobiles, TV
A8: FILTER | B8: =FILTER(Data!A2:L401,(Data!D2:D401="Pune")*(Data!L2:L401>20000),"None") | C8: 21 Pune orders above ₹20,000 (all columns)
A9: GROUPBY | B9: =GROUPBY(Data!D2:D401,Data!L2:L401,SUM,,,-2) | C9: Pune 2,033,249; Delhi 2,010,827; Bengaluru 1,928,644; Mumbai 1,829,975; Chennai 1,156,409; Gurugram 994,508
A10: PIVOTBY | B10: =PIVOTBY(Data!D2:D401,Data!F2:F401,Data!L2:L401,SUM) | C10: City × Category revenue grid (same as sheet 13)
A11: TAKE + SORT | B11: =TAKE(SORT(Data!A2:L401,12,-1),5) | C11: Top 5 orders by amount
A12: SEQUENCE | B12: =SEQUENCE(12,1,DATE(2026,4,1),31) | C12: 12 dates ~1 month apart from 01-Apr-2026
A13: TEXTSPLIT | B13: =TEXTSPLIT("NOR-1042-MUM","-") | C13: NOR | 1042 | MUM
A14: TEXTBEFORE / AFTER | B14: =TEXTAFTER("asha@example.com","@") | C14: example.com
A15: VSTACK | B15: =VSTACK(Jan!A2:E50,Feb!A2:E50) | C15: Two sheets appended into one list
A16: LET | B16: =LET(s,SUM(Data!L2:L401),c,SUM(Data!M2:M401),(s-c)/s) | C16: Overall margin % (see 18 Dashboard)
... A21: PY (Python in Excel) | B21: =PY(xl("Data!A1:N401",headers=True).groupby("City")["Amount"].sum()) | C21: Python result inside a cell

Sheet 16 Power Query
A1: 16 · Power Query: repeatable cleaning (steps)
A2: Do these steps on your own monthly files. Every click is recorded and replays on Refresh.
A3: ← Index
A5: # | B5: Step | C5: Result
A6: 1 | B6: Get Data → From File → From Folder → pick a folder of monthly CSVs → Combine & Transform | C6: One query combining every file
A7: 2 | B7: Check column types (ABC/123/calendar icons); set OrderDate to Date using locale English (India) for dd-mm-yyyy | C7: Correct types
A8: 3 | B8: Home → Remove Columns (keep only needed ones) | C8: Smaller, faster
A9: 4 | B9: Transform → Format → Trim and Clean on text columns; Replace Values for typos | C9: Clean text
A10: 5 | B10: Filter rows: remove blanks and test orders | C10: Valid rows only
A11: 6 | B11: Add Column → Custom Column: [Qty] * [UnitPrice] * (1 - [Discount]) | C11: Amount column
A12: 7 | B12: Home → Merge Queries with a Products query on ProductID (Left Outer) → expand Category | C12: VLOOKUP replacement
A13: 8 | B13: Select ID columns → Transform → Unpivot Other Columns (if months are across columns) | C13: Tidy long format
A14: 9 | B14: Transform → Group By City: Sum of Amount | C14: Optional summary
A15: 10 | B15: Close & Load To → Table (or Only Create Connection + Data Model) | C15: Output
A16: 11 | B16: Next month: drop new file into the folder → Data → Refresh All | C16: Automation
B18: M code example: = Table.AddColumn(#"Changed Type", "Amount", each [Qty] * [UnitPrice] * (1 - [Discount]), type number)

Sheet 17 Charts
A1: 17 · Charts built from formulas (column, line, pie, combo-style)
A2: The tables below are live formulas on the Data sheet; the charts update when data changes.
A3: ← Index
A5: Month | B5: Revenue | C5: Profit | D5: Margin %
A6: 46113 | B6: =SUMIFS(Data!$L$2:$L$401,Data!$B$2:$B$401,">="&A6,Data!$B$2:$B$401,"<="&EOMONTH(A6,0)) | C6: =SUMIFS(Data!$N$2:$N$401,Data!$B$2:$B$401,">="&A6,Data!$B$2:$B$401,"<="&EOMONTH(A6,0)) | D6: =IF(B6=0,0,C6/B6)
A7: 46143 | B7: =SUMIFS(Data!$L$2:$L$401,Data!$B$2:$B$401,">="&A7,Data!$B$2:$B$401,"<="&EOMONTH(A7,0)) | C7: =SUMIFS(Data!$N$2:$N$401,Data!$B$2:$B$401,">="&A7,Data!$B$2:$B$401,"<="&EOMONTH(A7,0)) | D7: =IF(B7=0,0,C7/B7)
A8: 46174 | B8: =SUMIFS(Data!$L$2:$L$401,Data!$B$2:$B$401,">="&A8,Data!$B$2:$B$401,"<="&EOMONTH(A8,0)) | C8: =SUMIFS(Data!$N$2:$N$401,Data!$B$2:$B$401,">="&A8,Data!$B$2:$B$401,"<="&EOMONTH(A8,0)) | D8: =IF(B8=0,0,C8/B8)
A9: 46204 | B9: =SUMIFS(Data!$L$2:$L$401,Data!$B$2:$B$401,">="&A9,Data!$B$2:$B$401,"<="&EOMONTH(A9,0)) | C9: =SUMIFS(Data!$N$2:$N$401,Data!$B$2:$B$401,">="&A9,Data!$B$2:$B$401,"<="&EOMONTH(A9,0)) | D9: =IF(B9=0,0,C9/B9)
A10: 46235 | B10: =SUMIFS(Data!$L$2:$L$401,Data!$B$2:$B$401,">="&A10,Data!$B$2:$B$401,"<="&EOMONTH(A10,0)) | C10: =SUMIFS(Data!$N$2:$N$401,Data!$B$2:$B$401,">="&A10,Data!$B$2:$B$401,"<="&EOMONTH(A10,0)) | D10: =IF(B10=0,0,C10/B10)
A11: 46266 | B11: =SUMIFS(Data!$L$2:$L$401,Data!$B$2:$B$401,">="&A11,Data!$B$2:$B$401,"<="&EOMONTH(A11,0)) | C11: =SUMIFS(Data!$N$2:$N$401,Data!$B$2:$B$401,">="&A11,Data!$B$2:$B$401,"<="&EOMONTH(A11,0)) | D11: =IF(B11=0,0,C11/B11)
A14: Category | B14: Revenue
A15: Mobiles | B15: =SUMIFS(Data!$L$2:$L$401,Data!$F$2:$F$401,A15)
A16: Laptops | B16: =SUMIFS(Data!$L$2:$L$401,Data!$F$2:$F$401,A16)
A17: Audio | B17: =SUMIFS(Data!$L$2:$L$401,Data!$F$2:$F$401,A17)
A18: Accessories | B18: =SUMIFS(Data!$L$2:$L$401,Data!$F$2:$F$401,A18)
A19: TV | B19: =SUMIFS(Data!$L$2:$L$401,Data!$F$2:$F$401,A19)

Sheet 18 Dashboard Case Study
A1: 18 · Case study: monthly sales dashboard for a 6-store electronics chain
A2: Scenario: the regional manager wants a one-page review. Pick the month in B5 (blue). Every number below is a live formula on the Data sheet (sample data).
A3: ← Index
A5: Month (first day) | B5: 46266
A7: KPI | B7: This month | C7: Last month | D7: Change %
A8: Revenue (₹) | B8: =SUMIFS(Data!$L$2:$L$401,Data!$B$2:$B$401,">="&$B$5,Data!$B$2:$B$401,"<="&EOMONTH($B$5,0)) | C8: =SUMIFS(Data!$L$2:$L$401,Data!$B$2:$B$401,">="&EDATE($B$5,-1),Data!$B$2:$B$401,"<="&EOMONTH($B$5,-1)) | D8: =IFERROR(B8/C8-1,0)
A9: Orders | B9: =COUNTIFS(Data!$B$2:$B$401,">="&$B$5,Data!$B$2:$B$401,"<="&EOMONTH($B$5,0)) | C9: =COUNTIFS(Data!$B$2:$B$401,">="&EDATE($B$5,-1),Data!$B$2:$B$401,"<="&EOMONTH($B$5,-1)) | D9: =IFERROR(B9/C9-1,0)
A10: Avg order value (₹) | B10: =IFERROR(B8/B9,0) | C10: =IFERROR(C8/C9,0) | D10: =IFERROR(B10/C10-1,0)
A11: Profit (₹) | B11: =SUMIFS(Data!$N$2:$N$401,Data!$B$2:$B$401,">="&$B$5,Data!$B$2:$B$401,"<="&EOMONTH($B$5,0)) | C11: =SUMIFS(Data!$N$2:$N$401,Data!$B$2:$B$401,">="&EDATE($B$5,-1),Data!$B$2:$B$401,"<="&EOMONTH($B$5,-1)) | D11: =IFERROR(B11/C11-1,0)
A12: Margin % | B12: =IFERROR(B11/B8,0) | C12: =IFERROR(C11/C8,0) | D12: =IFERROR(B12/C12-1,0)
A13: Warranty attach rate | B13: =IFERROR(COUNTIFS(Data!$B$2:$B$401,">="&$B$5,Data!$B$2:$B$401,"<="&EOMONTH($B$5,0),Data!$K$2:$K$401,"Yes")/B9,0) | C13: =IFERROR(COUNTIFS(Data!$B$2:$B$401,">="&EDATE($B$5,-1),Data!$B$2:$B$401,"<="&EOMONTH($B$5,-1),Data!$K$2:$K$401,"Yes")/C9,0) | D13: =IFERROR(B13/C13-1,0)
A15: Store league | B15: Revenue | C15: Orders | D15: AOV | E15: Rank | F15: Share %
A16: S01 Andheri, Mumbai | B16: =SUMIFS(Data!$L$2:$L$401,Data!$C$2:$C$401,"S01",Data!$B$2:$B$401,">="&$B$5,Data!$B$2:$B$401,"<="&EOMONTH($B$5,0)) | C16: =COUNTIFS(Data!$C$2:$C$401,"S01",Data!$B$2:$B$401,">="&$B$5,Data!$B$2:$B$401,"<="&EOMONTH($B$5,0)) | D16: =IFERROR(B16/C16,0) | E16: =_xlfn.RANK.EQ(B16,$B$16:$B$21) | F16: =IFERROR(B16/SUM($B$16:$B$21),0)
A17: S02 FC Road, Pune | B17: =SUMIFS(Data!$L$2:$L$401,Data!$C$2:$C$401,"S02",Data!$B$2:$B$401,">="&$B$5,Data!$B$2:$B$401,"<="&EOMONTH($B$5,0)) | C17: =COUNTIFS(Data!$C$2:$C$401,"S02",Data!$B$2:$B$401,">="&$B$5,Data!$B$2:$B$401,"<="&EOMONTH($B$5,0)) | D17: =IFERROR(B17/C17,0) | E17: =_xlfn.RANK.EQ(B17,$B$16:$B$21) | F17: =IFERROR(B17/SUM($B$16:$B$21),0)
A18: S03 Connaught Place, Delhi | B18: =SUMIFS(Data!$L$2:$L$401,Data!$C$2:$C$401,"S03",Data!$B$2:$B$401,">="&$B$5,Data!$B$2:$B$401,"<="&EOMONTH($B$5,0)) | C18: =COUNTIFS(Data!$C$2:$C$401,"S03",Data!$B$2:$B$401,">="&$B$5,Data!$B$2:$B$401,"<="&EOMONTH($B$5,0)) | D18: =IFERROR(B18/C18,0) | E18: =_xlfn.RANK.EQ(B18,$B$16:$B$21) | F18: =IFERROR(B18/SUM($B$16:$B$21),0)
A19: S04 Indiranagar, Bengaluru | B19: =SUMIFS(Data!$L$2:$L$401,Data!$C$2:$C$401,"S04",Data!$B$2:$B$401,">="&$B$5,Data!$B$2:$B$401,"<="&EOMONTH($B$5,0)) | C19: =COUNTIFS(Data!$C$2:$C$401,"S04",Data!$B$2:$B$401,">="&$B$5,Data!$B$2:$B$401,"<="&EOMONTH($B$5,0)) | D19: =IFERROR(B19/C19,0) | E19: =_xlfn.RANK.EQ(B19,$B$16:$B$21) | F19: =IFERROR(B19/SUM($B$16:$B$21),0)
A20: S05 T Nagar, Chennai | B20: =SUMIFS(Data!$L$2:$L$401,Data!$C$2:$C$401,"S05",Data!$B$2:$B$401,">="&$B$5,Data!$B$2:$B$401,"<="&EOMONTH($B$5,0)) | C20: =COUNTIFS(Data!$C$2:$C$401,"S05",Data!$B$2:$B$401,">="&$B$5,Data!$B$2:$B$401,"<="&EOMONTH($B$5,0)) | D20: =IFERROR(B20/C20,0) | E20: =_xlfn.RANK.EQ(B20,$B$16:$B$21) | F20: =IFERROR(B20/SUM($B$16:$B$21),0)
A21: S06 Cyber Hub, Gurugram | B21: =SUMIFS(Data!$L$2:$L$401,Data!$C$2:$C$401,"S06",Data!$B$2:$B$401,">="&$B$5,Data!$B$2:$B$401,"<="&EOMONTH($B$5,0)) | C21: =COUNTIFS(Data!$C$2:$C$401,"S06",Data!$B$2:$B$401,">="&$B$5,Data!$B$2:$B$401,"<="&EOMONTH($B$5,0)) | D21: =IFERROR(B21/C21,0) | E21: =_xlfn.RANK.EQ(B21,$B$16:$B$21) | F21: =IFERROR(B21/SUM($B$16:$B$21),0)
A23: Category | B23: Revenue | C23: Profit | D23: Margin %
A24: Mobiles | B24: =SUMIFS(Data!$L$2:$L$401,Data!$F$2:$F$401,A24,Data!$B$2:$B$401,">="&$B$5,Data!$B$2:$B$401,"<="&EOMONTH($B$5,0)) | C24: =SUMIFS(Data!$N$2:$N$401,Data!$F$2:$F$401,A24,Data!$B$2:$B$401,">="&$B$5,Data!$B$2:$B$401,"<="&EOMONTH($B$5,0)) | D24: =IFERROR(C24/B24,0)
A25: Laptops | B25: =SUMIFS(Data!$L$2:$L$401,Data!$F$2:$F$401,A25,Data!$B$2:$B$401,">="&$B$5,Data!$B$2:$B$401,"<="&EOMONTH($B$5,0)) | C25: =SUMIFS(Data!$N$2:$N$401,Data!$F$2:$F$401,A25,Data!$B$2:$B$401,">="&$B$5,Data!$B$2:$B$401,"<="&EOMONTH($B$5,0)) | D25: =IFERROR(C25/B25,0)
A26: Audio | B26: =SUMIFS(Data!$L$2:$L$401,Data!$F$2:$F$401,A26,Data!$B$2:$B$401,">="&$B$5,Data!$B$2:$B$401,"<="&EOMONTH($B$5,0)) | C26: =SUMIFS(Data!$N$2:$N$401,Data!$F$2:$F$401,A26,Data!$B$2:$B$401,">="&$B$5,Data!$B$2:$B$401,"<="&EOMONTH($B$5,0)) | D26: =IFERROR(C26/B26,0)
A27: Accessories | B27: =SUMIFS(Data!$L$2:$L$401,Data!$F$2:$F$401,A27,Data!$B$2:$B$401,">="&$B$5,Data!$B$2:$B$401,"<="&EOMONTH($B$5,0)) | C27: =SUMIFS(Data!$N$2:$N$401,Data!$F$2:$F$401,A27,Data!$B$2:$B$401,">="&$B$5,Data!$B$2:$B$401,"<="&EOMONTH($B$5,0)) | D27: =IFERROR(C27/B27,0)
A28: TV | B28: =SUMIFS(Data!$L$2:$L$401,Data!$F$2:$F$401,A28,Data!$B$2:$B$401,">="&$B$5,Data!$B$2:$B$401,"<="&EOMONTH($B$5,0)) | C28: =SUMIFS(Data!$N$2:$N$401,Data!$F$2:$F$401,A28,Data!$B$2:$B$401,">="&$B$5,Data!$B$2:$B$401,"<="&EOMONTH($B$5,0)) | D28: =IFERROR(C28/B28,0)
A30: Headline (auto): | B30: ="Revenue "&TEXT(B8,"₹#,##0")&" ("&TEXT(D8,"+0.0%;-0.0%")&" vs last month). Top store: "&INDEX(A16:A21,MATCH(1,E16:E21,0))&"."
A33: Questions this dashboard answers: Which store leads? Is revenue growing month on month? Which categories earn the best margin? Is warranty attachment improving?

Sheet 19 Automation & AI
A1: 19 · Automation & AI in Excel
A2: Copy these into Excel to try them. VBA needs the file saved as .xlsm; Copilot features need a Microsoft 365 Copilot licence.
A3: ← Index
A5: Technique | B5: How / code
A6: Record a macro | B6: View → Macros → Record Macro → do the steps → Stop. Edit with Alt+F11.
A7: VBA: format every sheet | B7: Sub FormatAll() Dim ws As Worksheet For Each ws In ThisWorkbook.Worksheets ws.Rows(1).Font.Bold = True ws.Columns.AutoFit Next ws End Sub
A8: VBA: export each sheet to PDF | B8: Sub ExportPDFs() Dim ws As Worksheet For Each ws In ThisWorkbook.Worksheets ws.ExportAsFixedFormat xlTypePDF, ThisWorkbook.Path & "\" & ws.Name & ".pdf" Next ws End Sub
A9: Office Script + Power Automate | B9: Excel for the web → Automate → Record Actions; then in Power Automate: Recurrence (Monday 9:00) → Run script → Send email with the file.
A10: Copilot prompts | B10: • "Add a column for profit margin and highlight negatives" • "Create a PivotTable of revenue by City and Category" • "Explain the formula in B30 of the dashboard" • "What are the top 3 insights in this data?"
A11: COPILOT function | B11: =COPILOT("Classify this customer review as Positive, Negative or Neutral", C2)
A12: Python in Excel | B12: =PY(xl("Data!A1:N401", headers=True).groupby("City")["Amount"].sum())
A13: External AI (ChatGPT / Claude / Gemini) | B13: "My sheet has columns OrderDate (B), City (D), Amount (L). Write one Excel formula for revenue in Pune for the month in cell B5." → test on a few rows you can check by hand.

Sheet Data
A1: OrderID | B1: OrderDate | C1: StoreID | D1: City | E1: ProductID | F1: Category | G1: Qty | H1: UnitPrice | I1: Discount | J1: CustomerType | K1: Warranty | L1: Amount | M1: Cost | N1: Profit | P1: Sample data (generated for practice): 400 orders, Apr–Sep 2026, fictional electronics chain.
A2: ORD-0165 | B2: 46113 | C2: S01 | D2: Mumbai | E2: P201 | F2: Laptops | G2: 1 | H2: 54999 | I2: 0 | J2: Online | K2: No | L2: =G2*H2*(1-I2) | M2: =G2*INDEX(Lookups!$E$3:$E$12,MATCH(E2,Lookups!$A$3:$A$12,0)) | N2: =L2-M2
A3: ORD-0174 | B3: 46113 | C3: S04 | D3: Bengaluru | E3: P401 | F3: Accessories | G3: 1 | H3: 1799 | I3: 0.1 | J3: Walk-in | K3: No | L3: =G3*H3*(1-I3) | M3: =G3*INDEX(Lookups!$E$3:$E$12,MATCH(E3,Lookups!$A$3:$A$12,0)) | N3: =L3-M3
A4: ORD-0334 | B4: 46113 | C4: S03 | D4: Delhi | E4: P402 | F4: Accessories | G4: 1 | H4: 1499 | I4: 0 | J4: Corporate | K4: No | L4: =G4*H4*(1-I4) | M4: =G4*INDEX(Lookups!$E$3:$E$12,MATCH(E4,Lookups!$A$3:$A$12,0)) | N4: =L4-M4
A5: ORD-0118 | B5: 46114 | C5: S04 | D5: Bengaluru | E5: P301 | F5: Audio | G5: 1 | H5: 2999 | I5: 0.05 | J5: Walk-in | K5: No | L5: =G5*H5*(1-I5) | M5: =G5*INDEX(Lookups!$E$3:$E$12,MATCH(E5,Lookups!$A$3:$A$12,0)) | N5: =L5-M5
A6: ORD-0130 | B6: 46114 | C6: S01 | D6: Mumbai | E6: P402 | F6: Accessories | G6: 3 | H6: 1499 | I6: 0 | J6: Corporate | K6: Yes | L6: =G6*H6*(1-I6) | M6: =G6*INDEX(Lookups!$E$3:$E$12,MATCH(E6,Lookups!$A$3:$A$12,0)) | N6: =L6-M6
A7: ORD-0200 | B7: 46115 | C7: S02 | D7: Pune | E7: P302 | F7: Audio | G7: 1 | H7: 4499 | I7: 0.05 | J7: Walk-in | K7: Yes | L7: =G7*H7*(1-I7) | M7: =G7*INDEX(Lookups!$E$3:$E$12,MATCH(E7,Lookups!$A$3:$A$12,0)) | N7: =L7-M7
A8: ORD-0266 | B8: 46115 | C8: S03 | D8: Delhi | E8: P102 | F8: Mobiles | G8: 2 | H8: 32999 | I8: 0.05 | J8: Walk-in | K8: Yes | L8: =G8*H8*(1-I8) | M8: =G8*INDEX(Lookups!$E$3:$E$12,MATCH(E8,Lookups!$A$3:$A$12,0)) | N8: =L8-M8
A9: ORD-0327 | B9: 46115 | C9: S01 | D9: Mumbai | E9: P101 | F9: Mobiles | G9: 1 | H9: 18999 | I9: 0 | J9: Walk-in | K9: Yes | L9: =G9*H9*(1-I9) | M9: =G9*INDEX(Lookups!$E$3:$E$12,MATCH(E9,Lookups!$A$3:$A$12,0)) | N9: =L9-M9
A10: ORD-0017 | B10: 46118 | C10: S05 | D10: Chennai | E10: P501 | F10: TV | G10: 1 | H10: 32999 | I10: 0 | J10: Online | K10: No | L10: =G10*H10*(1-I10) | M10: =G10*INDEX(Lookups!$E$3:$E$12,MATCH(E10,Lookups!$A$3:$A$12,0)) | N10: =L10-M10
A11: ORD-0277 | B11: 46118 | C11: S01 | D11: Mumbai | E11: P401 | F11: Accessories | G11: 1 | H11: 1799 | I11: 0.1 | J11: Corporate | K11: No | L11: =G11*H11*(1-I11) | M11: =G11*INDEX(Lookups!$E$3:$E$12,MATCH(E11,Lookups!$A$3:$A$12,0)) | N11: =L11-M11
A12: ORD-0302 | B12: 46118 | C12: S02 | D12: Pune | E12: P202 | F12: Laptops | G12: 3 | H12: 94999 | I12: 0 | J12: Walk-in | K12: Yes | L12: =G12*H12*(1-I12) | M12: =G12*INDEX(Lookups!$E$3:$E$12,MATCH(E12,Lookups!$A$3:$A$12,0)) | N12: =L12-M12
A13: ORD-0397 | B13: 46118 | C13: S06 | D13: Gurugram | E13: P102 | F13: Mobiles | G13: 1 | H13: 32999 | I13: 0.1 | J13: Online | K13: No | L13: =G13*H13*(1-I13) | M13: =G13*INDEX(Lookups!$E$3:$E$12,MATCH(E13,Lookups!$A$3:$A$12,0)) | N13: =L13-M13
... A401: ORD-0262 | B401: 46294 | C401: S06 | D401: Gurugram | E401: P401 | F401: Accessories | G401: 1 | H401: 1799 | I401: 0 | J401: Online | K401: No | L401: =G401*H401*(1-I401) | M401: =G401*INDEX(Lookups!$E$3:$E$12,MATCH(E401,Lookups!$A$3:$A$12,0)) | N401: =L401-M401

Sheet Lookups
A1: Lookup tables used by the formulas
A2: ProductID | B2: ProductName | C2: Category | D2: ListPrice | E2: UnitCost | G2: StoreID | H2: StoreName | I2: City | J2: State | L2: SalesFrom | M2: CommissionRate | O2: Holidays
A3: P101 | B3: Smartphone A | C3: Mobiles | D3: 18999 | E3: 15200 | G3: S01 | H3: Andheri | I3: Mumbai | J3: Maharashtra | L3: 0 | M3: 0.02 | O3: 46249
A4: P102 | B4: Smartphone B | C4: Mobiles | D4: 32999 | E4: 27100 | G4: S02 | H4: FC Road | I4: Pune | J4: Maharashtra | L4: 100000 | M4: 0.03 | O4: 46297
A5: P201 | B5: Laptop 14in | C5: Laptops | D5: 54999 | E5: 47300 | G5: S03 | H5: Connaught Place | I5: Delhi | J5: Delhi | L5: 500000 | M5: 0.05 | O5: 46315
A6: P202 | B6: Laptop Pro 16 | C6: Laptops | D6: 94999 | E6: 81200 | G6: S04 | H6: Indiranagar | I6: Bengaluru | J6: Karnataka | L6: 1000000 | M6: 0.07 | O6: 46334
A7: P301 | B7: Wireless Earbuds | C7: Audio | D7: 2999 | E7: 1650 | G7: S05 | H7: T Nagar | I7: Chennai | J7: Tamil Nadu
A8: P302 | B8: Bluetooth Speaker | C8: Audio | D8: 4499 | E8: 2900 | G8: S06 | H8: Cyber Hub | I8: Gurugram | J8: Haryana
A9: P401 | B9: Power Bank 20k | C9: Accessories | D9: 1799 | E9: 980
A10: P402 | B10: Charger 65W | C10: Accessories | D10: 1499 | E10: 760
A11: P501 | B11: Smart TV 43in | C11: TV | D11: 32999 | E11: 28400
A12: P502 | B12: Smart TV 55in | C12: TV | D12: 52999 | E12: 45100
